setup.py
shinkenplugins/__init__.py
shinkenplugins.plugins.aws_sqs_queue_size.egg-info/PKG-INFO
shinkenplugins.plugins.aws_sqs_queue_size.egg-info/SOURCES.txt
shinkenplugins.plugins.aws_sqs_queue_size.egg-info/dependency_links.txt
shinkenplugins.plugins.aws_sqs_queue_size.egg-info/entry_points.txt
shinkenplugins.plugins.aws_sqs_queue_size.egg-info/namespace_packages.txt
shinkenplugins.plugins.aws_sqs_queue_size.egg-info/requires.txt
shinkenplugins.plugins.aws_sqs_queue_size.egg-info/top_level.txt
shinkenplugins/plugins/__init__.py
shinkenplugins/plugins/aws_sqs_queue_size/__init__.py
shinkenplugins/plugins/aws_sqs_queue_size/aws_sqs_queue_size.py